Metadata-Version: 2.1
Name: bitex-kraken
Version: 1.0.0
Summary: Kraken extension for the Bitcoin Exchange (BitEx) REST API Framwork
Home-page: https://github.com/crypto-toolbox/bitex-kraken
Author: Nils Diefenbach
Author-email: foss@deepbrook.io
License: UNKNOWN
Project-URL: Bug Reports, https://github.com/crypto-toolbox/bitex-kraken/issues
Project-URL: Source, https://github.com/crypto-toolbox/bitex-kraken
Keywords: bitcoin rest api http exchange
Platform: UNKNOWN
Classifier: Development Status :: 3 - Alpha
Classifier: Intended Audience :: Developers
Classifier: License :: OSI Approved :: MIT License
Classifier: Programming Language :: Python :: 3.6
Classifier: Programming Language :: Python :: 3.7
Classifier: Programming Language :: Python :: 3.8
Requires-Python: >=3.6, <4
Provides-Extra: dev
Provides-Extra: test
Provides-Extra: ci
